{
"type": "FeatureCollection",
"name": "mora",
"crs": { "type": "name", "properties": { "name": "urn:ogc:def:crs:OGC:1.3:CRS84" } },
"features": [
{ "type": "Feature", "properties": { "fid": 1 }, "geometry": { "type": "Point", "coordinates": [ 27.552059248098001, 47.442882002271709 ] } }
]
}
